README
setup.cfg
setup.py
Flask_WTF_FlexWidgets.egg-info/PKG-INFO
Flask_WTF_FlexWidgets.egg-info/SOURCES.txt
Flask_WTF_FlexWidgets.egg-info/dependency_links.txt
Flask_WTF_FlexWidgets.egg-info/requires.txt
Flask_WTF_FlexWidgets.egg-info/top_level.txt
flask_wtf_flexwidgets/__init__.py
flask_wtf_flexwidgets/_compat.py