Metadata-Version: 1.1
Name: Flask-WTF-FlexWidgets
Version: 0.1.24
Summary: A flask extension that provides customizable WTF widgets and macros.
Home-page: https://github.com/bschumacher/Flask-WTF-FlexWidgets
Author: Bill Schumacher
Author-email: bill@servernet.co
License: LGPLv3
Keywords: flask wtf widget
Platform: UNKNOWN
Classifier: Programming Language :: Python :: 3
Classifier: Programming Language :: Python :: 3.5
